sopel_twitter/__init__.py
sopel_twitter-1.4.0.dist-info/licenses/COPYING
sopel_twitter-1.4.0.dist-info/METADATA
sopel_twitter-1.4.0.dist-info/WHEEL
sopel_twitter-1.4.0.dist-info/entry_points.txt
sopel_twitter-1.4.0.dist-info/top_level.txt
sopel_twitter-1.4.0.dist-info/RECORD
