Metadata-Version: 2.4
Name: sopel-twitter
Version: 1.4.0
Summary: A Twitter plugin for Sopel
Author-email: dgw <dgw@technobabbl.es>
License-Expression: EFL-2.0
Project-URL: Homepage, https://github.com/sopel-irc/sopel-twitter
Project-URL: Bug Tracker, https://github.com/sopel-irc/sopel-twitter/issues
Keywords: sopel,plugin,bot,irc
Platform: Linux x86, x86-64
Classifier: Intended Audience :: Developers
Classifier: Intended Audience :: System Administrators
Classifier: Topic :: Communications :: Chat :: Internet Relay Chat
Requires-Python: <4,>=3.9
License-File: COPYING
Requires-Dist: sopel<9,>=8
Requires-Dist: tweety-ns~=2.2
Dynamic: license-file
